{
  "id": "image",
  "type": "SharedSlice",
  "name": "Image",
  "description": "Image",
  "variations": [
    {
      "id": "default",
      "name": "Default",
      "docURL": "...",
      "version": "sktwi1xtmkfgx8626",
      "description": "Image",
      "primary": {
        "image": {
          "type": "Image",
          "config": { "label": "Image", "constraint": {}, "thumbnails": [] }
        },
        "caption": {
          "type": "StructuredText",
          "config": {
            "label": "Caption",
            "placeholder": "Optional - Caption under the image",
            "allowTargetBlank": true,
            "single": "paragraph,em,strong"
          }
        },
        "foo": {
          "type": "Boolean",
          "config": {
            "label": "Foo",
            "default_value": false,
            "placeholder_true": "true",
            "placeholder_false": "false"
          }
        }
      },
      "items": {},
      "imageUrl": "https://images.prismic.io/slicemachine-dev-mule/shared-slices/image/default/twe988zQK9p4OijW2oyET22Ps6g=.png?auto=compress%2Cformat"
    },
    {
      "id": "wide",
      "name": "Wide",
      "docURL": "...",
      "version": "sktwi1xtmkfgx8626",
      "description": "Image",
      "primary": {
        "image": {
          "type": "Image",
          "config": { "label": "Image", "constraint": {}, "thumbnails": [] }
        },
        "caption": {
          "type": "StructuredText",
          "config": {
            "label": "Caption",
            "placeholder": "Optional - Caption under the image",
            "allowTargetBlank": true,
            "single": "paragraph,em,strong"
          }
        }
      },
      "items": {},
      "imageUrl": "https://images.prismic.io/slicemachine-dev-mule/shared-slices/image/wide/xDGhbqN31RDj3OFpH+IWw48YF+w=.png?auto=compress%2Cformat"
    }
  ]
}
